tire_code_parser/__init__.py
tire_code_parser/parser.py
tire_code_parser-1.0.0.dist-info/LICENSE
tire_code_parser-1.0.0.dist-info/METADATA
tire_code_parser-1.0.0.dist-info/WHEEL
tire_code_parser-1.0.0.dist-info/top_level.txt
tire_code_parser-1.0.0.dist-info/RECORD
